clibot/__init__.py
clibot/__main__.py
clibot/__version__.py
clibot/animation.py
clibot/chat.py
clibot/cli.py
clibot/colors.py
clibot/config.py
clibot/streaming.py
clibot/system.py
clibot-0.1.4.1.dist-info/LICENSE
clibot-0.1.4.1.dist-info/METADATA
clibot-0.1.4.1.dist-info/WHEEL
clibot-0.1.4.1.dist-info/entry_points.txt
clibot-0.1.4.1.dist-info/top_level.txt
clibot-0.1.4.1.dist-info/RECORD
