Metadata-Version: 2.1
Name: clibot
Version: 0.1.4.1
Summary: An innovative command-line tool driven by powerful large language models, designed to accelerate task completion and maximize your productivity.
Home-page: https://github.com/linuztx/clibot
Author: linuztx
Author-email: linuztx@gmail.com
Classifier: Operating System :: OS Independent
Classifier: Intended Audience :: Information Technology
Classifier: License :: OSI Approved :: MIT License
Classifier: Intended Audience :: System Administrators
Classifier: Intended Audience :: Developers
Classifier: Programming Language :: Python :: 3 :: Only
Classifier: Programming Language :: Python :: 3.6
Classifier: Programming Language :: Python :: 3.7
Classifier: Programming Language :: Python :: 3.8
Classifier: Programming Language :: Python :: 3.9
Classifier: Programming Language :: Python :: 3.10
Classifier: Programming Language :: Python :: 3.11
Classifier: Programming Language :: Python :: 3.12
Requires-Python: >=3.6
License-File: LICENSE
Requires-Dist: openai ==1.34.0
Requires-Dist: requests ==2.32.3
Requires-Dist: colorama ==0.4.6
